quorumtoolbox/__init__.py
quorumtoolbox/constellation.py
quorumtoolbox/create_quorum_node.py
quorumtoolbox/genesis_template
quorumtoolbox/genesis_template_ibft
quorumtoolbox/geth.py
quorumtoolbox/ibft.py
quorumtoolbox/quorum_network.py
quorumtoolbox/quorum_node.py
quorumtoolbox/raft.py
quorumtoolbox/template_dir/blockchain/passwords.txt
quorumtoolbox/template_dir/blockchain/start_quorum_node.sh
quorumtoolbox/template_dir/blockchain/qdata/dd/geth/.dummy_for_git
quorumtoolbox/template_dir/blockchain/qdata/dd/keystore/.dummy_for_git
quorumtoolbox/template_dir/blockchain/qdata/dd/logs/.dummy_for_git
quorumtoolbox/template_dir/constellation/constellation.config
quorumtoolbox/template_dir/constellation/launch_constellation.sh
quorumtoolbox/template_dir/constellation/keys/.dummy_for_git
quorumtoolbox/template_dir/constellation/logs/.dummy_for_git
quorumtoolbox/template_dir/constellation/storage/.dummy_for_git
quorumtoolbox/template_dir/raft/raftid.json
quorumtoolbox/utils/__init__.py
quorumtoolbox/utils/bash_utils.py
quorumtoolbox/utils/constellation_utils.py
quorumtoolbox/utils/enode_utils.py
quorumtoolbox/utils/fs_utils.py
quorumtoolbox/utils/node_utils.py
quorumtoolbox/utils/templating.py
quorumtoolbox-4.0.1.dist-info/LICENSE
quorumtoolbox-4.0.1.dist-info/METADATA
quorumtoolbox-4.0.1.dist-info/WHEEL
quorumtoolbox-4.0.1.dist-info/top_level.txt
quorumtoolbox-4.0.1.dist-info/RECORD
