Metadata-Version: 2.1
Name: quorumtoolbox
Version: 4.0.1
Summary: Quorum Toolbox
Home-page: UNKNOWN
Author: UNKNOWN
Author-email: UNKNOWN
License: UNKNOWN
Platform: UNKNOWN
Requires-Dist: requests (>=2.20.0)
Requires-Dist: sh (>=1.12.14)
Requires-Dist: psutil (>=5.4.8)
